daemon_runner.py
setup.py
daemon_runner.egg-info/PKG-INFO
daemon_runner.egg-info/SOURCES.txt
daemon_runner.egg-info/dependency_links.txt
daemon_runner.egg-info/entry_points.txt
daemon_runner.egg-info/not-zip-safe
daemon_runner.egg-info/requires.txt
daemon_runner.egg-info/top_level.txt