Metadata-Version: 1.0
Name: daemon-runner
Version: 0.0.14
Summary: Simple command line runner on top of python-daemon
Home-page: http://www.hubspot.com
Author: HubSpot Developers
Author-email: dev@hubspot.com
License: UNKNOWN
Platform: any
